README.md
setup.py
servussimplifytext/__init__.py
servussimplifytext/servussimplifytext.py
servussimplifytext.egg-info/PKG-INFO
servussimplifytext.egg-info/SOURCES.txt
servussimplifytext.egg-info/dependency_links.txt
servussimplifytext.egg-info/top_level.txt